similar_dict/__init__.py
similar_dict/py.typed
similar_dict-0.2.0.dist-info/METADATA
similar_dict-0.2.0.dist-info/WHEEL
similar_dict-0.2.0.dist-info/RECORD
