Metadata-Version: 2.1
Name: similar-dict
Version: 0.2.0
Summary: Compare dictionary values by a type-or-value template
License: BSD-2-Clause
Author: Melvyn Sopacua
Author-email: 2403540-melvyn-sopacua@users.noreply.gitlab.com
Requires-Python: >=3.8,<4.0
Classifier: Development Status :: 4 - Beta
Classifier: Intended Audience :: Developers
Classifier: License :: OSI Approved :: BSD License
Classifier: Operating System :: OS Independent
Classifier: Programming Language :: Python :: 3
Classifier: Programming Language :: Python :: 3.8
Classifier: Programming Language :: Python :: 3.9
Classifier: Programming Language :: Python :: 3.10
Classifier: Programming Language :: Python :: 3.11
Classifier: Programming Language :: Python :: 3.12
Classifier: Programming Language :: Python :: 3 :: Only
Classifier: Programming Language :: Python :: 3.13
Classifier: Topic :: Software Development :: Testing
Requires-Dist: typing-extensions (>=4.8.0,<5.0.0)
